{
  "objectID": 314308,
  "isHighlight": false,
  "accessionNumber": "1983.542.2",
  "accessionYear": "1983",
  "isPublicDomain": false,
  "primaryImage": "",
  "primaryImageSmall": "",
  "additionalImages": [],
  "constituents": null,
  "department": "The Michael C. Rockefeller Wing",
  "objectName": "Bracelet",
  "title": "Bracelet",
  "culture": "Edo peoples",
  "period": "",
  "dynasty": "",
  "reign": "",
  "portfolio": "",
  "artistRole": "",
  "artistPrefix": "",
  "artistDisplayName": "",
  "artistDisplayBio": "",
  "artistSuffix": "",
  "artistAlphaSort": "",
  "artistNationality": "",
  "artistBeginDate": "",
  "artistEndDate": "",
  "artistGender": "",
  "artistWikidata_URL": "",
  "artistULAN_URL": "",
  "objectDate": "18th\u201319th century",
  "objectBeginDate": 1700,
  "objectEndDate": 1800,
  "medium": "Ivory",
  "dimensions": "W. 3 3/8 x D. 4 3/4 in. (8.6 x 12.1 cm)",
  "measurements": [
    {
      "elementName": "Overall",
      "elementDescription": null,
      "elementMeasurements": {
        "Depth": 12.065,
        "Width": 8.59
      }
    }
  ],
  "creditLine": "Anonymous Gift, 1983",
  "geographyType": "",
  "city": "Court of Benin",
  "state": "",
  "county": "",
  "country": "Nigeria",
  "region": "",
  "subregion": "",
  "locale": "",
  "locus": "",
  "excavation": "",
  "river": "",
  "classification": "Bone/Ivory-Ornaments",
  "rightsAndReproduction": "",
  "linkResource": "",
  "metadataDate": "2021-06-15T04:37:52.723Z",
  "repository": "Metropolitan Museum of Art, New York, NY",
  "objectURL": "https://www.metmuseum.org/art/collection/search/314308",
  "tags": null,
  "objectWikidata_URL": "",
  "isTimelineWork": false,
  "GalleryNumber": ""
}