{
  "objectID": 656,
  "isHighlight": false,
  "accessionNumber": "1972.225.4a, b",
  "accessionYear": "1972",
  "isPublicDomain": true,
  "primaryImage": "https://images.metmuseum.org/CRDImages/ad/original/DP234595.jpg",
  "primaryImageSmall": "https://images.metmuseum.org/CRDImages/ad/web-large/DP234595.jpg",
  "additionalImages": [],
  "constituents": null,
  "department": "The American Wing",
  "objectName": "Bottle",
  "title": "Bottle",
  "culture": "",
  "period": "",
  "dynasty": "",
  "reign": "",
  "portfolio": "",
  "artistRole": "",
  "artistPrefix": "",
  "artistDisplayName": "",
  "artistDisplayBio": "",
  "artistSuffix": "",
  "artistAlphaSort": "",
  "artistNationality": "",
  "artistBeginDate": "",
  "artistEndDate": "",
  "artistGender": "",
  "artistWikidata_URL": "",
  "artistULAN_URL": "",
  "objectDate": "1700\u20131800",
  "objectBeginDate": 1700,
  "objectEndDate": 1800,
  "medium": "Glass",
  "dimensions": "Overall: 7 7/16 in., 184 Grams (18.9 cm, 5.916 Troy Ounces)\r\nBase diameter: 1 5/8 in. (4.1 cm)\r\nOther (Height without stopper): 6 in. (15.2 cm)",
  "measurements": [
    {
      "elementName": "Overall",
      "elementDescription": null,
      "elementMeasurements": {
        "Height": 18.8913,
        "Length": 0.184
      }
    },
    {
      "elementName": "Other",
      "elementDescription": "Height without stopper",
      "elementMeasurements": {
        "Height": 15.24
      }
    },
    {
      "elementName": "Diam. of base",
      "elementDescription": null,
      "elementMeasurements": {
        "Diameter": 4.1275
      }
    }
  ],
  "creditLine": "Purchase, Rogers Fund and Mr. and Mrs. Marshall P. Blankarn Gift, 1972",
  "geographyType": "Possibly made in",
  "city": "",
  "state": "",
  "county": "",
  "country": "Ireland",
  "region": "",
  "subregion": "",
  "locale": "",
  "locus": "",
  "excavation": "",
  "river": "",
  "classification": "",
  "rightsAndReproduction": "",
  "linkResource": "",
  "metadataDate": "2021-04-06T04:41:04.967Z",
  "repository": "Metropolitan Museum of Art, New York, NY",
  "objectURL": "https://www.metmuseum.org/art/collection/search/656",
  "tags": null,
  "objectWikidata_URL": "",
  "isTimelineWork": false,
  "GalleryNumber": "774"
}