{
  "links": {
    "search": "http://www.rijksmuseum.nl/api/nl/collection"
  },
  "id": "en-BK-2012-67",
  "priref": "516507",
  "objectNumber": "BK-2012-67",
  "language": "en",
  "title": "Banyan",
  "copyrightHolder": null,
  "webImage": {
    "guid": "dbc7a1cb-cb48-4e80-8c23-b7964c0ee6c4",
    "offsetPercentageX": 50,
    "offsetPercentageY": 17,
    "width": 1626,
    "height": 2500,
    "url": "https://lh5.ggpht.com/iTwYLdmpzWYl4BlIqlMlpn1nnE7GswV2rQepELVOFowfUi_URI-_hY4IZHM5iZbdKIbWYnfBNIFlPeiX_O4ud7ew8Q=s0"
  },
  "colors": [],
  "colorsWithNormalization": [],
  "normalizedColors": [],
  "normalized32Colors": [],
  "titles": [],
  "description": "Huisjas van katoen bedrukt met floraal strooimotief in blokdruk, met opstaande kraag en revers. Model: getailleerd, met nauwsluitende lange mouwen met teruggeslagen manchetten met drie met dezelfde stof beklede knopen. Opstaande kraag en grote revers met ieder een gefestonneerd knoopsgat. Sluiting middenvoor met negen met dezelfde stof beklede knopen aan weerszijden en gefestonneerde knoopsgaten. Lange split op de rug. Steekzakken. Gevoerd met een geruite voering in oker, lichtbruin, beige en blauw ('Harlinger bont': linnen ketting, katoenen inslag?). Gekalandeerd. Stof: Europese katoendruk, blokdruk aangevuld met enige getekende partijen. Bruin fond waarop gestrooide boeketten en stelen van gedraaid koord in rood, blauw en wit.",
  "labelText": null,
  "objectTypes": [],
  "objectCollection": [
    "costumes and accessories"
  ],
  "makers": [
    {
      "name": "anonymous",
      "unFixedName": "anonymous",
      "placeOfBirth": null,
      "dateOfBirth": null,
      "dateOfBirthPrecision": null,
      "dateOfDeath": null,
      "dateOfDeathPrecision": null,
      "placeOfDeath": null,
      "occupation": [],
      "roles": [],
      "nationality": null,
      "biography": null,
      "productionPlaces": [
        "Europe"
      ],
      "qualification": null,
      "labelDesc": "anonymous, Europe"
    }
  ],
  "principalMakers": [
    {
      "name": "anonymous",
      "unFixedName": "anonymous",
      "placeOfBirth": null,
      "dateOfBirth": null,
      "dateOfBirthPrecision": null,
      "dateOfDeath": null,
      "dateOfDeathPrecision": null,
      "placeOfDeath": null,
      "occupation": [],
      "roles": [
        "maker"
      ],
      "nationality": null,
      "biography": null,
      "productionPlaces": [
        "Netherlands"
      ],
      "qualification": null,
      "labelDesc": "anonymous, Netherlands"
    }
  ],
  "plaqueDescriptionDutch": null,
  "plaqueDescriptionEnglish": null,
  "principalMaker": "anonymous",
  "artistRole": null,
  "associations": [],
  "acquisition": {
    "method": "purchase",
    "date": "2012-01-01T00:00:00",
    "creditLine": null
  },
  "exhibitions": [],
  "materials": [
    "cotton (textile)",
    "linen (material)"
  ],
  "techniques": [
    "printing"
  ],
  "productionPlaces": [
    "Netherlands",
    "Europe"
  ],
  "dating": {
    "presentingDate": "c. 1795",
    "sortingDate": 1795,
    "period": 18,
    "yearEarly": 1795,
    "yearLate": 1795
  },
  "classification": {
    "iconClassIdentifier": [],
    "iconClassDescription": [],
    "motifs": [],
    "events": [],
    "periods": [],
    "places": [],
    "people": [],
    "objectNumbers": [
      "BK-2012-67"
    ]
  },
  "hasImage": true,
  "historicalPersons": [],
  "inscriptions": [],
  "documentation": [],
  "catRefRPK": [],
  "principalOrFirstMaker": "anonymous",
  "dimensions": [
    {
      "unit": "cm",
      "type": "height",
      "precision": "c.",
      "part": null,
      "value": "138"
    }
  ],
  "physicalProperties": [],
  "physicalMedium": "printing",
  "longTitle": "Banyan, anonymous, c. 1795",
  "subTitle": "h c.138cm",
  "scLabelLine": "The Netherlands, c. 1795, cotton, linen",
  "label": {
    "title": "Banyan",
    "makerLine": "The Netherlands, c. 1795, cotton, linen",
    "description": "At the end of the 18th century housecoats increasingly featured the characteristics of an overcoat, such as setin sleeves, pockets, and a collar. The glazed cotton fabric of this housecoat was made in Europe. Printed cotton with delicate floral motifs on a dark ground was widely produced in Europe before the end of the 18th century. The coarse chequered lining known as \u2018Harlinger bont\u2019 was made in the city of Harlingen.",
    "notes": null,
    "date": "2016-02-29"
  },
  "showImage": true,
  "location": null
}