{
  "links": {
    "search": "http://www.rijksmuseum.nl/api/nl/collection"
  },
  "id": "en-BK-NM-9575-B",
  "priref": "453489",
  "objectNumber": "BK-NM-9575-B",
  "language": "en",
  "title": "Haardsteen van gebakken aarde met ruitvormige verdeling met twee medaillons van een man en vrouw",
  "copyrightHolder": null,
  "webImage": {
    "guid": "b6811d8a-de04-4c38-b4a0-8442f2434838",
    "offsetPercentageX": 50,
    "offsetPercentageY": 50,
    "width": 2500,
    "height": 1854,
    "url": "https://lh3.googleusercontent.com/5P6Ei3pdjr5AvnvF-oLb1p1AWGyM9i6hjbacHTsI9J5DCY97JluO4NN8yHrVampz0XaLShPsN-ga19Gwli9neN4dFA=s0"
  },
  "colors": [],
  "colorsWithNormalization": [],
  "normalizedColors": [],
  "normalized32Colors": [],
  "titles": [
    "Haardsteen van gebakken aarde met ruitvormige verdeling met twee medaillons van een man en vrouw"
  ],
  "description": "Haardsteen van gebakken aarde met ruitvormige verdeling. Twee medaillons van een man en vrouw.",
  "labelText": null,
  "objectTypes": [],
  "objectCollection": [],
  "makers": [],
  "principalMakers": [
    {
      "name": "anonymous",
      "unFixedName": "anonymous",
      "placeOfBirth": null,
      "dateOfBirth": null,
      "dateOfBirthPrecision": null,
      "dateOfDeath": null,
      "dateOfDeathPrecision": null,
      "placeOfDeath": null,
      "occupation": [],
      "roles": [
        "maker"
      ],
      "nationality": null,
      "biography": null,
      "productionPlaces": [
        "Southern Netherlands"
      ],
      "qualification": null,
      "labelDesc": "anonymous, Southern Netherlands"
    }
  ],
  "plaqueDescriptionDutch": null,
  "plaqueDescriptionEnglish": null,
  "principalMaker": "anonymous",
  "artistRole": null,
  "associations": [],
  "acquisition": {
    "method": "transfer",
    "date": "1892-01-01T00:00:00",
    "creditLine": null
  },
  "exhibitions": [],
  "materials": [
    "earthenware"
  ],
  "techniques": [],
  "productionPlaces": [
    "Southern Netherlands"
  ],
  "dating": {
    "presentingDate": "c. 1400 - c. 1950",
    "sortingDate": 1400,
    "period": 14,
    "yearEarly": 1400,
    "yearLate": 1950
  },
  "classification": {
    "iconClassIdentifier": [],
    "iconClassDescription": [],
    "motifs": [],
    "events": [],
    "periods": [],
    "places": [],
    "people": [],
    "objectNumbers": [
      "BK-NM-9575-B"
    ]
  },
  "hasImage": true,
  "historicalPersons": [],
  "inscriptions": [],
  "documentation": [],
  "catRefRPK": [],
  "principalOrFirstMaker": "anonymous",
  "dimensions": [
    {
      "unit": "cm",
      "type": "height",
      "precision": null,
      "part": null,
      "value": "9.5"
    },
    {
      "unit": "cm",
      "type": "width",
      "precision": null,
      "part": null,
      "value": "14.5"
    },
    {
      "unit": "cm",
      "type": "thickness",
      "precision": null,
      "part": null,
      "value": "6"
    }
  ],
  "physicalProperties": [],
  "physicalMedium": "earthenware",
  "longTitle": "Haardsteen van gebakken aarde met ruitvormige verdeling met twee medaillons van een man en vrouw, anonymous, c. 1400 - c. 1950",
  "subTitle": "h 9.5cm \u00d7 w 14.5cm \u00d7 t 6cm",
  "scLabelLine": "anonymous, c. 1400 - c. 1950, earthenware",
  "label": {
    "title": null,
    "makerLine": null,
    "description": null,
    "notes": null,
    "date": null
  },
  "showImage": true,
  "location": null
}