{
  "links": {
    "search": "http://www.rijksmuseum.nl/api/nl/collection"
  },
  "id": "en-RP-F-2001-7-361-6",
  "priref": "635479",
  "objectNumber": "RP-F-2001-7-361-6",
  "language": "en",
  "title": "Grasmere, from Red Bank",
  "copyrightHolder": null,
  "webImage": {
    "guid": "8e534303-e822-4112-8451-54882c2ca779",
    "offsetPercentageX": 50,
    "offsetPercentageY": 50,
    "width": 2500,
    "height": 1569,
    "url": "https://lh3.googleusercontent.com/y3Hej6aYJFzPtcHGZVoO6NUDV3bXocj3dJKSPeZ0z6b5aaGdiH34m3TeRL1ga6C90hq3AEJ_A3IpAwt_J2V8WAxKNMQ=s0"
  },
  "colors": [],
  "colorsWithNormalization": [],
  "normalizedColors": [],
  "normalized32Colors": [],
  "titles": [
    "Grasmere, from Red Bank"
  ],
  "description": null,
  "labelText": null,
  "objectTypes": [
    "photograph"
  ],
  "objectCollection": [],
  "makers": [],
  "principalMakers": [
    {
      "name": "Thomas Ogle",
      "unFixedName": "Ogle, Thomas",
      "placeOfBirth": null,
      "dateOfBirth": null,
      "dateOfBirthPrecision": null,
      "dateOfDeath": null,
      "dateOfDeathPrecision": null,
      "placeOfDeath": null,
      "occupation": [],
      "roles": [],
      "nationality": null,
      "biography": null,
      "productionPlaces": [],
      "qualification": null,
      "labelDesc": "Thomas Ogle"
    }
  ],
  "plaqueDescriptionDutch": null,
  "plaqueDescriptionEnglish": null,
  "principalMaker": "Thomas Ogle",
  "artistRole": null,
  "associations": [],
  "acquisition": {
    "method": "purchase",
    "date": "2001-01-01T00:00:00",
    "creditLine": "Purchased with the support of the Mondriaan Stichting, the Prins Bernhard Cultuurfonds, the VSBfonds, the Paul Huf Fonds/Rijksmuseum Fonds and the Egbert Kunstfonds"
  },
  "exhibitions": [],
  "materials": [
    "photographic support"
  ],
  "techniques": [
    "albumen print"
  ],
  "productionPlaces": [],
  "dating": {
    "presentingDate": "c. 1860 - in or before 1870",
    "sortingDate": 1860,
    "period": 19,
    "yearEarly": 1860,
    "yearLate": 1870
  },
  "classification": {
    "iconClassIdentifier": [
      "25H214"
    ],
    "iconClassDescription": [
      "lake"
    ],
    "motifs": [],
    "events": [],
    "periods": [],
    "places": [
      "Grasmere"
    ],
    "people": [],
    "objectNumbers": [
      "RP-F-2001-7-361-6"
    ]
  },
  "hasImage": true,
  "historicalPersons": [],
  "inscriptions": [],
  "documentation": [],
  "catRefRPK": [],
  "principalOrFirstMaker": "Thomas Ogle",
  "dimensions": [
    {
      "unit": "mm",
      "type": "height",
      "precision": null,
      "part": null,
      "value": "91"
    },
    {
      "unit": "mm",
      "type": "width",
      "precision": null,
      "part": null,
      "value": "85"
    }
  ],
  "physicalProperties": [],
  "physicalMedium": "albumen print",
  "longTitle": "Grasmere, from Red Bank, Thomas Ogle, c. 1860 - in or before 1870",
  "subTitle": "h 91mm \u00d7 w 85mm",
  "scLabelLine": "Thomas Ogle, c. 1860 - in or before 1870, albumen print",
  "label": {
    "title": null,
    "makerLine": null,
    "description": null,
    "notes": null,
    "date": null
  },
  "showImage": true,
  "location": null
}