{
  "links": {
    "search": "http://www.rijksmuseum.nl/api/nl/collection"
  },
  "id": "en-RP-F-2017-185-17",
  "priref": "831269",
  "objectNumber": "RP-F-2017-185-17",
  "language": "en",
  "title": "Vijf foto's van het reisgezelschap op het schip S.Y. Sapphire en in Noorwegen",
  "copyrightHolder": null,
  "webImage": null,
  "colors": [],
  "colorsWithNormalization": [],
  "normalizedColors": [],
  "normalized32Colors": [],
  "titles": [
    "Vijf foto's van het reisgezelschap op het schip S.Y. Sapphire en in Noorwegen"
  ],
  "description": "Deze foto's maken deel uit van een album.",
  "labelText": null,
  "objectTypes": [
    "photograph"
  ],
  "objectCollection": [],
  "makers": [
    {
      "name": "Duchess of Bedford",
      "unFixedName": "Duchess of Bedford",
      "placeOfBirth": null,
      "dateOfBirth": null,
      "dateOfBirthPrecision": null,
      "dateOfDeath": null,
      "dateOfDeathPrecision": null,
      "placeOfDeath": null,
      "occupation": [],
      "roles": [],
      "nationality": null,
      "biography": null,
      "productionPlaces": [],
      "qualification": "mentioned on object",
      "labelDesc": "mentioned on object Duchess of Bedford"
    },
    {
      "name": "J. Tooth",
      "unFixedName": "Tooth, J.",
      "placeOfBirth": null,
      "dateOfBirth": null,
      "dateOfBirthPrecision": null,
      "dateOfDeath": null,
      "dateOfDeathPrecision": null,
      "placeOfDeath": null,
      "occupation": [],
      "roles": [],
      "nationality": null,
      "biography": null,
      "productionPlaces": [],
      "qualification": "mentioned on object",
      "labelDesc": "mentioned on object J. Tooth"
    },
    {
      "name": "F. Green (fotograaf)",
      "unFixedName": "Green, F. (fotograaf)",
      "placeOfBirth": null,
      "dateOfBirth": null,
      "dateOfBirthPrecision": null,
      "dateOfDeath": null,
      "dateOfDeathPrecision": null,
      "placeOfDeath": null,
      "occupation": [],
      "roles": [],
      "nationality": null,
      "biography": null,
      "productionPlaces": [],
      "qualification": "mentioned on object",
      "labelDesc": "mentioned on object F. Green (fotograaf)"
    }
  ],
  "principalMakers": [
    {
      "name": "Mary Russell",
      "unFixedName": "Russell, Mary",
      "placeOfBirth": "Stockbridge",
      "dateOfBirth": "1865-09-26",
      "dateOfBirthPrecision": null,
      "dateOfDeath": "1937-03-22",
      "dateOfDeathPrecision": null,
      "placeOfDeath": "Noordzee",
      "occupation": [],
      "roles": [],
      "nationality": null,
      "biography": null,
      "productionPlaces": [],
      "qualification": "mentioned on object",
      "labelDesc": "mentioned on object Mary Russell (26-sep-1865 - 22-mrt-1937)"
    }
  ],
  "plaqueDescriptionDutch": null,
  "plaqueDescriptionEnglish": null,
  "principalMaker": "Mary Russell",
  "artistRole": null,
  "associations": [],
  "acquisition": {
    "method": "purchase",
    "date": "2017-10-27T00:00:00",
    "creditLine": null
  },
  "exhibitions": [],
  "materials": [
    "paper",
    "baryta paper"
  ],
  "techniques": [],
  "productionPlaces": [],
  "dating": {
    "presentingDate": "1901",
    "sortingDate": 1901,
    "period": 20,
    "yearEarly": 1901,
    "yearLate": 1901
  },
  "classification": {
    "iconClassIdentifier": [
      "41D2423",
      "41D2422",
      "48C6151",
      "46C5135"
    ],
    "iconClassDescription": [
      "historical costume",
      "dress-up party",
      "camera ~ photography",
      "(traveller) resting in the open air"
    ],
    "motifs": [],
    "events": [],
    "periods": [],
    "places": [
      "Noorwegen"
    ],
    "people": [
      "Duchess of Bedford",
      "Russell, Mary",
      "Marshall, I.",
      "Green, F. (fotograaf)",
      "Tooth, J.",
      "Russell, Herbrand",
      "Russell, Hastings"
    ],
    "objectNumbers": [
      "RP-F-2017-185-17"
    ]
  },
  "hasImage": false,
  "historicalPersons": [
    "Duchess of Bedford",
    "Russell, Mary",
    "Marshall, I.",
    "Green, F. (fotograaf)",
    "Tooth, J.",
    "Russell, Herbrand",
    "Russell, Hastings"
  ],
  "inscriptions": [],
  "documentation": [],
  "catRefRPK": [],
  "principalOrFirstMaker": "Mary Russell",
  "dimensions": [
    {
      "unit": "mm",
      "type": "height",
      "precision": null,
      "part": null,
      "value": "317"
    },
    {
      "unit": "mm",
      "type": "width",
      "precision": null,
      "part": null,
      "value": "273"
    }
  ],
  "physicalProperties": [],
  "physicalMedium": "paper",
  "longTitle": "Vijf foto's van het reisgezelschap op het schip S.Y. Sapphire en in Noorwegen, Mary Russell, 1901",
  "subTitle": "h 317mm \u00d7 w 273mm",
  "scLabelLine": "Mary Russell, 1901, paper",
  "label": {
    "title": null,
    "makerLine": null,
    "description": null,
    "notes": null,
    "date": null
  },
  "showImage": false,
  "location": null
}