{
  "links": {
    "search": "http://www.rijksmuseum.nl/api/nl/collection"
  },
  "id": "en-RP-P-1951-632",
  "priref": "118381",
  "objectNumber": "RP-P-1951-632",
  "language": "en",
  "title": "Maria met Christus en Johannes de Doper als kinderen",
  "copyrightHolder": null,
  "webImage": {
    "guid": "89f57b35-0176-4cbd-9d85-14a0e4e2bdb4",
    "offsetPercentageX": 50,
    "offsetPercentageY": 50,
    "width": 1796,
    "height": 2500,
    "url": "https://lh3.googleusercontent.com/AiOZuA-4XPQTYlWe4D0KVREQP8pnOa0exkTforzwtK7qMSWdcGovuGQV7LCUsnB6WNlFFicOcCEE31-Z6Nu7hlqIH1sEDJUWF4sDiFw=s0"
  },
  "colors": [],
  "colorsWithNormalization": [],
  "normalizedColors": [],
  "normalized32Colors": [],
  "titles": [
    "Maria met Christus en Johannes de Doper als kinderen",
    "The Virgin with the Infant Jesus, and St. John / La Vierge avec L'Enfant Jesus, et St. Jean"
  ],
  "description": "Naast het adres van de uitgever staat: In Monsr. Pigage's Catalogue of the Dusseldorf Gallery, this Subject is No. 61.",
  "labelText": null,
  "objectTypes": [
    "print"
  ],
  "objectCollection": [
    "prints"
  ],
  "makers": [
    {
      "name": "Valentine & Rupert Green",
      "unFixedName": "Green, Valentine & Rupert",
      "placeOfBirth": null,
      "dateOfBirth": null,
      "dateOfBirthPrecision": null,
      "dateOfDeath": null,
      "dateOfDeathPrecision": null,
      "placeOfDeath": null,
      "occupation": [
        "publisher"
      ],
      "roles": [
        "publisher"
      ],
      "nationality": null,
      "biography": null,
      "productionPlaces": [
        "London"
      ],
      "qualification": "mentioned on object",
      "labelDesc": "mentioned on object Valentine & Rupert Green, London"
    },
    {
      "name": "Valentine & Rupert Green",
      "unFixedName": "Green, Valentine & Rupert",
      "placeOfBirth": null,
      "dateOfBirth": null,
      "dateOfBirthPrecision": null,
      "dateOfDeath": null,
      "dateOfDeathPrecision": null,
      "placeOfDeath": null,
      "occupation": [
        "publisher"
      ],
      "roles": [],
      "nationality": null,
      "biography": null,
      "productionPlaces": [],
      "qualification": "mentioned on object",
      "labelDesc": "mentioned on object Valentine & Rupert Green"
    },
    {
      "name": "Karel Theodoor van Beieren (hertog)",
      "unFixedName": "Beieren, Karel Theodoor van (hertog)",
      "placeOfBirth": "Brussel (stad)",
      "dateOfBirth": "1724-11-12",
      "dateOfBirthPrecision": null,
      "dateOfDeath": "1799-02-16",
      "dateOfDeathPrecision": null,
      "placeOfDeath": "M\u00fcnchen",
      "occupation": [],
      "roles": [],
      "nationality": null,
      "biography": null,
      "productionPlaces": [],
      "qualification": "mentioned on object",
      "labelDesc": "mentioned on object Karel Theodoor van Beieren (hertog) (12-nov-1724 - 16-feb-1799)"
    }
  ],
  "principalMakers": [
    {
      "name": "Valentine Green",
      "unFixedName": "Green, Valentine",
      "placeOfBirth": "Salford",
      "dateOfBirth": "1739-10-16",
      "dateOfBirthPrecision": null,
      "dateOfDeath": "1813-06-29",
      "dateOfDeathPrecision": null,
      "placeOfDeath": "Londen",
      "occupation": [
        "print maker"
      ],
      "roles": [
        "print maker"
      ],
      "nationality": null,
      "biography": null,
      "productionPlaces": [],
      "qualification": "mentioned on object",
      "labelDesc": "mentioned on object Valentine Green (16-okt-1739 - 29-jun-1813)"
    }
  ],
  "plaqueDescriptionDutch": null,
  "plaqueDescriptionEnglish": null,
  "principalMaker": "Valentine Green",
  "artistRole": null,
  "associations": [],
  "acquisition": {
    "method": "purchase",
    "date": "1951-01-01T00:00:00",
    "creditLine": "Purchased with the support of the F.G. Waller-Fonds"
  },
  "exhibitions": [],
  "materials": [
    "paper"
  ],
  "techniques": [],
  "productionPlaces": [
    "London"
  ],
  "dating": {
    "presentingDate": "1794",
    "sortingDate": 1794,
    "period": 18,
    "yearEarly": 1794,
    "yearLate": 1794
  },
  "classification": {
    "iconClassIdentifier": [
      "73B831"
    ],
    "iconClassDescription": [
      "Mary and the Christ-child with John the Baptist (as child)"
    ],
    "motifs": [],
    "events": [],
    "periods": [],
    "places": [],
    "people": [],
    "objectNumbers": [
      "RP-P-1951-632"
    ]
  },
  "hasImage": true,
  "historicalPersons": [],
  "inscriptions": [],
  "documentation": [],
  "catRefRPK": [
    "Aantal staten bekend"
  ],
  "principalOrFirstMaker": "Valentine Green",
  "dimensions": [
    {
      "unit": "mm",
      "type": "height",
      "precision": null,
      "part": null,
      "value": "622"
    },
    {
      "unit": "mm",
      "type": "width",
      "precision": null,
      "part": null,
      "value": "417"
    }
  ],
  "physicalProperties": [],
  "physicalMedium": "paper",
  "longTitle": "Maria met Christus en Johannes de Doper als kinderen, Valentine Green, 1794",
  "subTitle": "h 622mm \u00d7 w 417mm",
  "scLabelLine": "Valentine Green, 1794, paper",
  "label": {
    "title": null,
    "makerLine": null,
    "description": null,
    "notes": null,
    "date": null
  },
  "showImage": true,
  "location": null
}