{
  "links": {
    "search": "http://www.rijksmuseum.nl/api/nl/collection"
  },
  "id": "en-RP-P-OB-52.133",
  "priref": "111894",
  "objectNumber": "RP-P-OB-52.133",
  "language": "en",
  "title": "Vignet met de personificatie van de Rede",
  "copyrightHolder": null,
  "webImage": {
    "guid": "5cbefcfb-5f59-4a9f-ab3f-a65b165b5431",
    "offsetPercentageX": 50,
    "offsetPercentageY": 50,
    "width": 3960,
    "height": 3029,
    "url": "https://lh3.ggpht.com/__9sCCqCA4tYiSL4q3C8OLinKOTAQ1hw7Y-RN0QGer_eiBEuE6mk6Zl1A76FloOlsLR5aK5RJzaWbnMkmP-j6D6gwQ=s0"
  },
  "colors": [
    {
      "percentage": 42,
      "hex": "#E5E2D4"
    },
    {
      "percentage": 15,
      "hex": " #7A776B"
    },
    {
      "percentage": 13,
      "hex": " #C2BFB3"
    },
    {
      "percentage": 11,
      "hex": " #9F9C91"
    },
    {
      "percentage": 7,
      "hex": " #5D5A4F"
    },
    {
      "percentage": 6,
      "hex": " #F9F8F4"
    },
    {
      "percentage": 2,
      "hex": " #39372E"
    }
  ],
  "colorsWithNormalization": [
    {
      "originalHex": "#E5E2D4",
      "normalizedHex": "#FBF6E1"
    },
    {
      "originalHex": " #7A776B",
      "normalizedHex": "#737C84"
    },
    {
      "originalHex": " #C2BFB3",
      "normalizedHex": "#FBF6E1"
    },
    {
      "originalHex": " #9F9C91",
      "normalizedHex": "#737C84"
    },
    {
      "originalHex": " #5D5A4F",
      "normalizedHex": "#737C84"
    },
    {
      "originalHex": " #F9F8F4",
      "normalizedHex": "#FBF6E1"
    },
    {
      "originalHex": " #39372E",
      "normalizedHex": "#2F4F4F"
    }
  ],
  "normalizedColors": [
    {
      "percentage": 42,
      "hex": "#FDF5E6"
    },
    {
      "percentage": 15,
      "hex": " #808080"
    },
    {
      "percentage": 13,
      "hex": " #C0C0C0"
    },
    {
      "percentage": 11,
      "hex": " #A9A9A9"
    },
    {
      "percentage": 10,
      "hex": " #696969"
    },
    {
      "percentage": 6,
      "hex": " #F5F5F5"
    }
  ],
  "normalized32Colors": [],
  "titles": [
    "Vignet met de personificatie van de Rede",
    "Deugden en ondeugden"
  ],
  "description": "Vignet met de beeltenis van de gepersonifieerde Rede in een architecturale omlijsting waarin onderaan een cartouche met een weegschaal is geplaatst. De Rede trapt met haar voet twee duivelse figuren tegen de grond, in haar handen houdt ze teugels en een zweep vast. De prent maakt deel uit van een reeks boekillustraties over deugden en ondeugden.",
  "labelText": null,
  "objectTypes": [
    "print"
  ],
  "objectCollection": [
    "prints"
  ],
  "makers": [],
  "principalMakers": [
    {
      "name": "Jacob Folkema",
      "unFixedName": "Folkema, Jacob",
      "placeOfBirth": "Dokkum",
      "dateOfBirth": "1692",
      "dateOfBirthPrecision": null,
      "dateOfDeath": "1767",
      "dateOfDeathPrecision": null,
      "placeOfDeath": "Amsterdam",
      "occupation": [
        "print maker",
        "draughtsman"
      ],
      "roles": [
        "print maker"
      ],
      "nationality": null,
      "biography": null,
      "productionPlaces": [],
      "qualification": "mentioned on object",
      "labelDesc": "mentioned on object Jacob Folkema (1692 - 1767)"
    }
  ],
  "plaqueDescriptionDutch": null,
  "plaqueDescriptionEnglish": null,
  "principalMaker": "Jacob Folkema",
  "artistRole": null,
  "associations": [],
  "acquisition": {
    "method": "transfer",
    "date": "1816-01-01T00:00:00",
    "creditLine": null
  },
  "exhibitions": [],
  "materials": [
    "paper"
  ],
  "techniques": [
    "etching"
  ],
  "productionPlaces": [],
  "dating": {
    "presentingDate": "1723 - 1767",
    "sortingDate": 1723,
    "period": 18,
    "yearEarly": 1723,
    "yearLate": 1767
  },
  "classification": {
    "iconClassIdentifier": [
      "52B51"
    ],
    "iconClassDescription": [
      "Reason; 'Ragione' (Ripa)"
    ],
    "motifs": [],
    "events": [],
    "periods": [],
    "places": [],
    "people": [],
    "objectNumbers": [
      "RP-P-OB-52.133"
    ]
  },
  "hasImage": true,
  "historicalPersons": [],
  "inscriptions": [],
  "documentation": [],
  "catRefRPK": [],
  "principalOrFirstMaker": "Jacob Folkema",
  "dimensions": [
    {
      "unit": "mm",
      "type": "height",
      "precision": null,
      "part": null,
      "value": "92"
    },
    {
      "unit": "mm",
      "type": "width",
      "precision": null,
      "part": null,
      "value": "122"
    }
  ],
  "physicalProperties": [],
  "physicalMedium": "etching",
  "longTitle": "Vignet met de personificatie van de Rede, Jacob Folkema, 1723 - 1767",
  "subTitle": "h 92mm \u00d7 w 122mm",
  "scLabelLine": "Jacob Folkema, 1723 - 1767, etching",
  "label": {
    "title": null,
    "makerLine": null,
    "description": null,
    "notes": null,
    "date": null
  },
  "showImage": true,
  "location": null
}