{
  "links": {
    "search": "http://www.rijksmuseum.nl/api/nl/collection"
  },
  "id": "en-RP-P-1886-A-10908Q",
  "priref": "486810",
  "objectNumber": "RP-P-1886-A-10908Q",
  "language": "en",
  "title": "Lijkstatie van Willem IV, 1752, plaat 17",
  "copyrightHolder": null,
  "webImage": {
    "guid": "52c8d08f-fe88-4fd3-b1e0-1065de40bb79",
    "offsetPercentageX": 50,
    "offsetPercentageY": 50,
    "width": 2500,
    "height": 1306,
    "url": "https://lh3.ggpht.com/a1NIKHgVXHxJkMvwuOj7CHzt9XTo8PfQLEyihZ8rNRjFQfyOsPnOKRrDJHI5efiCPOGYpV8Tv3PPwHnVklR23xuMLg=s0"
  },
  "colors": [],
  "colorsWithNormalization": [],
  "normalizedColors": [],
  "normalized32Colors": [],
  "titles": [
    "Lijkstatie van Willem IV, 1752, plaat 17",
    "De Bibliothecarius  / De Lyf Medicus en Professor Winter (...)",
    "Lyk-staetsie van zyne doorluchtigste Hoogheid den Heere Willem [IV] Carel Hendrik Friso, Prince van Orange en Nassau... gehouden den IV Februari 1752"
  ],
  "description": "Leden van de stadhouderlijke hofhouding, waaronder de bibliothecaris en lijfarts, gevolgd door trommelslagers en trompetters. In de marge het onderschrift in Nederlands, Frans en Engels. Onderdeel van een serie van 41 platen van de begrafenisstoet van stadhouder Willem IV te Delft op 4 februari 1752. Genummerd rechtsboven: 17.",
  "labelText": null,
  "objectTypes": [
    "print"
  ],
  "objectCollection": [
    "prints"
  ],
  "makers": [],
  "principalMakers": [
    {
      "name": "Jan Punt",
      "unFixedName": "Punt, Jan",
      "placeOfBirth": "Amsterdam",
      "dateOfBirth": "1711-04-02",
      "dateOfBirthPrecision": null,
      "dateOfDeath": "1779-12-18",
      "dateOfDeathPrecision": null,
      "placeOfDeath": "Amsterdam",
      "occupation": [
        "print maker",
        "draughtsman",
        "publisher"
      ],
      "roles": [
        "print maker"
      ],
      "nationality": null,
      "biography": null,
      "productionPlaces": [
        "Northern Netherlands"
      ],
      "qualification": "mentioned on object",
      "labelDesc": "mentioned on object Jan Punt (02-apr-1711 - 18-dec-1779), Northern Netherlands"
    }
  ],
  "plaqueDescriptionDutch": null,
  "plaqueDescriptionEnglish": null,
  "principalMaker": "Jan Punt",
  "artistRole": null,
  "associations": [],
  "acquisition": {
    "method": "purchase",
    "date": "1886-01-01T00:00:00",
    "creditLine": null
  },
  "exhibitions": [],
  "materials": [
    "paper"
  ],
  "techniques": [
    "etching",
    "engraving"
  ],
  "productionPlaces": [
    "Northern Netherlands"
  ],
  "dating": {
    "presentingDate": "1753",
    "sortingDate": 1753,
    "period": 18,
    "yearEarly": 1753,
    "yearLate": 1753
  },
  "classification": {
    "iconClassIdentifier": [
      "42E22",
      "44B152",
      "45C9",
      "49M9(+2)"
    ],
    "iconClassDescription": [
      "cortege, funeral procession",
      "royal household; courtiers, retinue, train",
      "military music",
      "public library (+ scholar, scientist in non-work situations)"
    ],
    "motifs": [],
    "events": [
      "Dood van Willem IV (1751)",
      "Begrafenis van Willem IV (1752)"
    ],
    "periods": [
      "1752-02-041752-02-04"
    ],
    "places": [
      "Delft"
    ],
    "people": [
      "Willem IV (prins van Oranje-Nassau)"
    ],
    "objectNumbers": [
      "RP-P-1886-A-10908Q"
    ]
  },
  "hasImage": true,
  "historicalPersons": [
    "Willem IV (prins van Oranje-Nassau)"
  ],
  "inscriptions": [],
  "documentation": [
    "Frederik Muller, De Nederlandsche geschiedenis in platen : beredeneerde beschrijving van Nederlandsche historieplaten, zinneprenten en historische kaarten, 4 delen, F. Muller, Amsterdam 1863-1882, dl. II (jaren 1702 tot 1795), p. 190-191, nr. 4032/17."
  ],
  "catRefRPK": [
    "FMH 4032",
    "4032",
    "Atlas van Stolk 4033",
    "4033"
  ],
  "principalOrFirstMaker": "Jan Punt",
  "dimensions": [
    {
      "unit": "mm",
      "type": "height",
      "precision": null,
      "part": null,
      "value": "270"
    },
    {
      "unit": "mm",
      "type": "width",
      "precision": null,
      "part": null,
      "value": "560"
    }
  ],
  "physicalProperties": [],
  "physicalMedium": "etching",
  "longTitle": "Lijkstatie van Willem IV, 1752, plaat 17, Jan Punt, 1753",
  "subTitle": "h 270mm \u00d7 w 560mm",
  "scLabelLine": "Jan Punt, 1753, etching",
  "label": {
    "title": null,
    "makerLine": null,
    "description": null,
    "notes": null,
    "date": null
  },
  "showImage": true,
  "location": null
}