{
  "links": {
    "search": "http://www.rijksmuseum.nl/api/nl/collection"
  },
  "id": "en-RP-P-OB-207.312",
  "priref": "564660",
  "objectNumber": "RP-P-OB-207.312",
  "language": "en",
  "title": "Van held van Speyk wordt hier een tafereel gegeven, / Hij redde Oud-Hollands vlag ten koste van zijn leven",
  "copyrightHolder": null,
  "webImage": {
    "guid": "4f473dc7-e63c-4e14-a711-474b9e021401",
    "offsetPercentageX": 50,
    "offsetPercentageY": 50,
    "width": 2500,
    "height": 1987,
    "url": "https://lh3.googleusercontent.com/cFkoeZyf30cAZLXsGa6QMPQ8OzdQDEeymNePZbBDE4a98R_lhSAF2zHkhTHj-tpS2CdkdPIdflqNyxuc4l137hk40uA=s0"
  },
  "colors": [],
  "colorsWithNormalization": [],
  "normalizedColors": [],
  "normalized32Colors": [],
  "titles": [
    "Van held van Speyk wordt hier een tafereel gegeven, / Hij redde Oud-Hollands vlag ten koste van zijn leven"
  ],
  "description": "Blad met 12 voorstellingen over het leven en de zelfopoffering van J.C.J. Van Speijk tijdens de strijd tegen de Belgen. Onder elke afbeelding een tweeregelig vers. Genummerd midden boven: 35.",
  "labelText": null,
  "objectTypes": [
    "print"
  ],
  "objectCollection": [
    "prints"
  ],
  "makers": [
    {
      "name": "anonymous",
      "unFixedName": "anonymous",
      "placeOfBirth": null,
      "dateOfBirth": null,
      "dateOfBirthPrecision": null,
      "dateOfDeath": null,
      "dateOfDeathPrecision": null,
      "placeOfDeath": null,
      "occupation": [],
      "roles": [
        "print maker"
      ],
      "nationality": null,
      "biography": null,
      "productionPlaces": [
        "Netherlands"
      ],
      "qualification": null,
      "labelDesc": "anonymous, Netherlands"
    }
  ],
  "principalMakers": [
    {
      "name": "Lutkie & Cranenburg",
      "unFixedName": "Lutkie & Cranenburg",
      "placeOfBirth": null,
      "dateOfBirth": null,
      "dateOfBirthPrecision": null,
      "dateOfDeath": null,
      "dateOfDeathPrecision": null,
      "placeOfDeath": null,
      "occupation": [
        "publisher",
        "printer",
        "bookseller"
      ],
      "roles": [
        "publisher"
      ],
      "nationality": null,
      "biography": null,
      "productionPlaces": [
        "Netherlands"
      ],
      "qualification": null,
      "labelDesc": "Lutkie & Cranenburg, Netherlands"
    }
  ],
  "plaqueDescriptionDutch": null,
  "plaqueDescriptionEnglish": null,
  "principalMaker": "Lutkie & Cranenburg",
  "artistRole": null,
  "associations": [],
  "acquisition": {
    "method": "gift",
    "date": "1923-01-01T00:00:00",
    "creditLine": "Gift of F.G. Waller, Amsterdam"
  },
  "exhibitions": [],
  "materials": [
    "paper"
  ],
  "techniques": [
    "letterpress printing"
  ],
  "productionPlaces": [
    "Netherlands",
    "Netherlands"
  ],
  "dating": {
    "presentingDate": "1848 - 1881",
    "sortingDate": 1848,
    "period": 19,
    "yearEarly": 1848,
    "yearLate": 1881
  },
  "classification": {
    "iconClassIdentifier": [
      "45H3",
      "44F",
      "42B6"
    ],
    "iconClassDescription": [
      "battle",
      "revolutie, opstand",
      "orphans"
    ],
    "motifs": [],
    "events": [
      "Belgische Revolutie",
      "Zelfopoffering van Jan van Speijk"
    ],
    "periods": [
      "1831"
    ],
    "places": [
      "Belgi\u00eb",
      "Nederland"
    ],
    "people": [
      "Speijk, Jan Carel Josephus van"
    ],
    "objectNumbers": [
      "RP-P-OB-207.312"
    ]
  },
  "hasImage": true,
  "historicalPersons": [
    "Speijk, Jan Carel Josephus van"
  ],
  "inscriptions": [],
  "documentation": [],
  "catRefRPK": [],
  "principalOrFirstMaker": "Lutkie & Cranenburg",
  "dimensions": [
    {
      "unit": "mm",
      "type": "height",
      "precision": null,
      "part": null,
      "value": "305"
    },
    {
      "unit": "mm",
      "type": "width",
      "precision": null,
      "part": null,
      "value": "387"
    }
  ],
  "physicalProperties": [],
  "physicalMedium": "letterpress printing",
  "longTitle": "Van held van Speyk wordt hier een tafereel gegeven, / Hij redde Oud-Hollands vlag ten koste van zijn leven, Lutkie & Cranenburg, 1848 - 1881",
  "subTitle": "h 305mm \u00d7 w 387mm",
  "scLabelLine": "Lutkie & Cranenburg, 1848 - 1881, letterpress printing",
  "label": {
    "title": null,
    "makerLine": null,
    "description": null,
    "notes": null,
    "date": null
  },
  "showImage": true,
  "location": null
}